{"layoutId":"d201e777","title":"Main Map Page","width":"100%","height":"100%","backgroundColor":"transparent","display":"block","flexDirection":"row","layoutElements":[{"type":"div","swimAttributes":[],"styleAttributes":{"display":"none"},"id":"b3a6b5bb","htmlAttributes":{"class":"sideMenuOpen"},"children":[{"type":"div","swimAttributes":[],"styleAttributes":[],"id":"9863d483","children":[{"type":"h3","swimAttributes":[],"styleAttributes":{"margin":"2px","font-weight":"100"},"id":"68e19cee","content":"Transit Agencies","name":"Menu Title"},{"type":"div","swimAttributes":[],"styleAttributes":[],"id":"9567a26b","htmlAttributes":{"class":"toggleButton","onmouseup":"page.toggleMenu()"},"name":"Menu Button"}],"content":"","name":"menu header"},{"type":"div","swimAttributes":[],"styleAttributes":[],"id":"cfb9be55","name":"filterList","htmlAttributes":{"class":"filterList"}}],"name":"menu container","content":""},{"type":"div","swimAttributes":{"width":"100%","height":"100%"},"styleAttributes":{"position":"absolute","top":"0px","bottom":"0px","right":"0px","left":"0px"},"id":"8a639a18","children":[{"type":"div","swimAttributes":[],"styleAttributes":{"display":"none"},"id":"207ff9f9","content":"","htmlAttributes":{"class":"timestampContainer"},"children":[{"type":"div","swimAttributes":[],"styleAttributes":{"class":"simBarContainer"},"id":"c0ebccfc","content":"","name":"timestamp div"},{"type":"div","swimAttributes":[],"styleAttributes":[],"id":"e5bdb7f9","name":"sim progress bar container","children":[{"type":"div","swimAttributes":[],"styleAttributes":[],"id":"f9574fe3","name":"bar bg","children":[{"type":"div","swimAttributes":[],"styleAttributes":[],"id":"3e5db015","content":"","name":"bar fg","htmlAttributes":{"class":"simBarFg"}}],"htmlAttributes":{"class":"simBarBg"}}],"htmlAttributes":{"class":"simBarContainer"}},{"type":"div","id":"93c39404","content":"LIVE"}],"name":"timestamp container"},{"type":"map","swimAttributes":{"width":"100%","height":"100%","pitch":"0","zoom":"10","centerLat":"33.91241157822809","centerLong":"-118.17316984486507","tween":"7200","mapStyle":"mapbox://styles/mapbox/dark-v10","controlPlacment":"bottom-right"},"styleAttributes":[],"id":"e55efe2c","content":"","children":[{"type":"overlay","swimAttributes":{"width":"100%"},"styleAttributes":{"flex-grow":"0"},"id":"121246ec","content":""}]}]},{"type":"div","swimAttributes":[],"styleAttributes":{"flex-grow":"0","position":"absolute","width":"350px","height":"400px","background-color":"rgba(100,100,100,0.0)","right":"0px","top":"0px","display":"none","margin-top":"74px","flex-direction":"column","overflow":"auto"},"id":"9d8b996e","name":"","content":"","children":[{"type":"div","swimAttributes":[],"styleAttributes":{"display":"flex","flex-direction":"column","backdrop-filter":"blur(5px) saturate(0%)","grid-area":"pie1","background-color":"rgba(12,17,18,0.5)","flex-grow":"1"},"id":"9a24dbe8","content":"","children":[{"type":"h4","swimAttributes":[],"styleAttributes":{"left":"0px","display":"none"},"id":"1e8a6673","content":"Route List","htmlAttributes":{"class":"pieHeaderr"}},{"type":"h4","swimAttributes":[],"styleAttributes":[],"id":"1e8a6674","content":"Total Routes:","htmlAttributes":{"class":"pieHeader"},"children":[{"type":"span","swimAttributes":{"width":"100%"},"styleAttributes":{"flex-grow":0},"id":"1a6cff34","content":"0"}]},{"type":"div","swimAttributes":[],"styleAttributes":{"color":"white","height":"100%","overflow":"auto"},"id":"cec61646","content":"","htmlAttributes":{"class":"routeList"}}],"name":"on ground pie container"}]}],"pageCss":"/assets/css/style.css","pageJsFile":"","systemLayout":false,"lastEdit":1582746428291}